<InputMapper Version="0.0.2.2">
    <Settings>
        <MouseSensitivity>1.0</MouseSensitivity>
        <WheelSensitivity>5.0</WheelSensitivity>
        <Joystick ID="0">
            <Descr>-unused-</Descr>
            <Identifier>DirectInput:{001E36B7-5DBA-4C4F-A8C9-044FB10A0000}</Identifier>
            <NameFilter/>
            <ForceFeedback>false</ForceFeedback>
            <Axis ID="0" Type="Auto" Deadzone="0.07" Power="1.0"/>
            <Axis ID="1" Type="Auto" Deadzone="0.07" Power="1.0"/>
            <Axis ID="2" Type="Auto" Deadzone="0.0" Power="1.0"/>
            <Axis ID="3" Type="Auto" Deadzone="0.07" Power="1.0"/>
            <Axis ID="4" Type="Auto" Deadzone="0.07" Power="1.0"/>
            <Axis ID="5" Type="Auto" Deadzone="0.0" Power="1.0"/>
            <Axis ID="6" Type="Auto" Deadzone="0.0" Power="1.0"/>
            <Axis ID="7" Type="Auto" Deadzone="0.0" Power="1.0"/>
        </Joystick>
        <Joystick ID="1">
            <Descr>-unused-</Descr>
            <Identifier>DirectInput:{001E36B7-5DBA-4C4F-A8C9-044FB10A0001}</Identifier>
            <NameFilter/>
            <ForceFeedback>false</ForceFeedback>
            <Axis ID="0" Type="Auto" Deadzone="0.07" Power="1.0"/>
            <Axis ID="1" Type="Auto" Deadzone="0.07" Power="1.0"/>
            <Axis ID="2" Type="Auto" Deadzone="0.0" Power="1.0"/>
            <Axis ID="3" Type="Auto" Deadzone="0.07" Power="1.0"/>
            <Axis ID="4" Type="Auto" Deadzone="0.07" Power="1.0"/>
            <Axis ID="5" Type="Auto" Deadzone="0.0" Power="1.0"/>
            <Axis ID="6" Type="Auto" Deadzone="0.0" Power="1.0"/>
            <Axis ID="7" Type="Auto" Deadzone="0.0" Power="1.0"/>
        </Joystick>
        <Joystick ID="2">
            <Descr>-unused-</Descr>
            <Identifier/>
            <NameFilter/>
            <ForceFeedback>false</ForceFeedback>
            <Axis ID="0" Type="Auto" Deadzone="0.075" Power="1.0"/>
            <Axis ID="1" Type="Auto" Deadzone="0.075" Power="1.0"/>
            <Axis ID="2" Type="Auto" Deadzone="0.0" Power="1.0"/>
            <Axis ID="3" Type="Auto" Deadzone="0.075" Power="1.0"/>
            <Axis ID="4" Type="Auto" Deadzone="0.075" Power="1.0"/>
            <Axis ID="5" Type="Auto" Deadzone="0.0" Power="1.0"/>
            <Axis ID="6" Type="Auto" Deadzone="0.0" Power="1.0"/>
            <Axis ID="7" Type="Auto" Deadzone="0.0" Power="1.0"/>
        </Joystick>
        <Joystick ID="3">
            <Descr>-unused-</Descr>
            <Identifier/>
            <NameFilter/>
            <ForceFeedback>false</ForceFeedback>
            <Axis ID="0" Type="Auto" Deadzone="0.075" Power="1.0"/>
            <Axis ID="1" Type="Auto" Deadzone="0.075" Power="1.0"/>
            <Axis ID="2" Type="Auto" Deadzone="0.0" Power="1.0"/>
            <Axis ID="3" Type="Auto" Deadzone="0.075" Power="1.0"/>
            <Axis ID="4" Type="Auto" Deadzone="0.075" Power="1.0"/>
            <Axis ID="5" Type="Auto" Deadzone="0.0" Power="1.0"/>
            <Axis ID="6" Type="Auto" Deadzone="0.0" Power="1.0"/>
            <Axis ID="7" Type="Auto" Deadzone="0.0" Power="1.0"/>
        </Joystick>
    </Settings>
    <Group ID="0" Name="UI_System_Input_Group_Basic_Flight" ExcludeGroups="1;6" Order="0"/>
    <Group ID="1" Name="UI_System_Input_Group_Capital_Flight" ExcludeGroups="0;6" Order="1"/>
    <Group ID="2" Name="UI_System_Input_Group_Common_Flight" ExcludeGroups="6" Order="2"/>
    <Group ID="3" Name="UI_System_Input_Group_Weapons" ExcludeGroups="6" Order="3"/>
    <Group ID="4" Name="UI_System_Input_Group_Systems" ExcludeGroups="6" Order="4"/>
    <Group ID="5" Name="UI_System_Input_Group_View" ExcludeGroups="6" Order="5"/>
    <Group ID="6" Name="UI_System_Input_Group_Other" ExcludeGroups="" Order="6"/>
    <Input Event="Yaw" Name="UI_Event_Yaw" Tooltip="UI_Event_Yaw_Tooltip" Keys="joystick1axis0" Type="AxisX" GroupID="0" Order="0"/>
    <Input Event="YawLeft" Name="UI_Event_YawLeft" Tooltip="UI_Event_YawLeft_Tooltip" Type="ToggleButton" GroupID="0" Order="100"/>
    <Input Event="YawRight" Name="UI_Event_YawRight" Tooltip="UI_Event_YawRight_Tooltip" Type="ToggleButton" GroupID="0" Order="200"/>
    <Input Event="Pitch" Name="UI_Event_Pitch" Tooltip="UI_Event_Pitch_Tooltip" Keys="joystick1axis1" Type="AxisY" GroupID="0" Order="300"/>
    <Input Event="PitchUp" Name="UI_Event_PitchUp" Tooltip="UI_Event_PitchUp_Tooltip" Type="ToggleButton" GroupID="0" Order="400"/>
    <Input Event="PitchDown" Name="UI_Event_PitchDown" Tooltip="UI_Event_PitchDown_Tooltip" Type="ToggleButton" GroupID="0" Order="500"/>
    <Input Event="Roll" Name="UI_Event_Roll" Tooltip="UI_Event_Roll_Tooltip" SecKeys="joystick1axis2" Type="AxisX" GroupID="0" Order="600"/>
    <Input Event="RollLeft" Name="UI_Event_RollLeft" Tooltip="UI_Event_RollLeft_Tooltip" Keys="q" Type="ToggleButton" GroupID="0" Order="700"/>
    <Input Event="RollRight" Name="UI_Event_RollRight" Tooltip="UI_Event_RollRight_Tooltip" Keys="e" Type="ToggleButton" GroupID="0" Order="800"/>
    <Input Event="StrafeX" Name="UI_Event_StrafeX" Tooltip="UI_Event_StrafeX_Tooltip" SecKeys="joystick0axis0" Type="AxisX" GroupID="0" Order="900"/>
    <Input Event="StrafeLeft" Name="UI_Event_StrafeLeft" Tooltip="UI_Event_StrafeLeft_Tooltip" Keys="a" Type="ToggleButton" GroupID="0" Order="1000"/>
    <Input Event="StrafeRight" Name="UI_Event_StrafeRight" Tooltip="UI_Event_StrafeRight_Tooltip" Keys="d" Type="ToggleButton" GroupID="0" Order="1100"/>
    <Input Event="StrafeY" Name="UI_Event_StrafeY" Tooltip="UI_Event_StrafeY_Tooltip" SecKeys="joystick0axis2" Type="AxisY" GroupID="0" Order="1200"/>
    <Input Event="StrafeUp" Name="UI_Event_StrafeUp" Tooltip="UI_Event_StrafeUp_Tooltip" Keys="r" Type="ToggleButton" GroupID="0" Order="1300"/>
    <Input Event="StrafeDown" Name="UI_Event_StrafeDown" Tooltip="UI_Event_StrafeDown_Tooltip" Keys="f" Type="ToggleButton" GroupID="0" Order="1400"/>
    <Input Event="StrafeZ" Name="UI_Event_StrafeZ" Tooltip="UI_Event_StrafeZ_Tooltip" SecKeys="joystick0axis1" Reverse="true" Type="AxisY" GroupID="0" Order="1500"/>
    <Input Event="Forward" Name="UI_Event_Forward" Tooltip="UI_Event_Forward_Tooltip" Keys="w" Type="ToggleButton" GroupID="0" Order="1600"/>
    <Input Event="Backward" Name="UI_Event_Backward" Tooltip="UI_Event_Backward_Tooltip" Keys="s" Type="ToggleButton" GroupID="0" Order="1700"/>
    <Input Event="Turbo" Name="UI_Event_Turbo" Tooltip="UI_Event_Turbo_Tooltip" Keys="leftshift" SecKeys="joystick0button3" Type="ToggleButton" GroupID="0" Order="1800"/>
    <Input Event="Brake" Name="UI_Event_Brake" Tooltip="UI_Event_Brake_Tooltip" Keys="space" SecKeys="joystick0button0 + rightctrl + joystick0button3" Type="ToggleButton" GroupID="0" Order="1900"/>
    <Input Event="ViewYaw" Name="UI_Event_ViewYaw" Tooltip="UI_Event_ViewYaw_Tooltip" Keys="leftctrl + mouseaxisx" SecKeys="joystick0arrow0" Type="AxisX" GroupID="0" Order="2000"/>
    <Input Event="ViewPitch" Name="UI_Event_ViewPitch" Tooltip="UI_Event_ViewPitch_Tooltip" Keys="leftctrl + mouseaxisy" SecKeys="joystick0arrow0" Type="AxisY" GroupID="0" Order="2100"/>
    <Input Event="CapYaw" Name="UI_Event_Yaw" Tooltip="UI_Event_Yaw_Tooltip" SecKeys="joystick1axis0" Type="AxisX" GroupID="1" Order="10000"/>
    <Input Event="CapYawLeft" Name="UI_Event_YawLeft" Tooltip="UI_Event_YawLeft_Tooltip" Keys="a" Type="ToggleButton" GroupID="1" Order="10100"/>
    <Input Event="CapYawRight" Name="UI_Event_YawRight" Tooltip="UI_Event_YawRight_Tooltip" Keys="d" Type="ToggleButton" GroupID="1" Order="10200"/>
    <Input Event="CapPitch" Name="UI_Event_Pitch" Tooltip="UI_Event_Pitch_Tooltip" SecKeys="joystick1axis1" Type="AxisY" GroupID="1" Order="10300"/>
    <Input Event="CapPitchUp" Name="UI_Event_PitchUp" Tooltip="UI_Event_PitchUp_Tooltip" Keys="s" Type="ToggleButton" GroupID="1" Order="10400"/>
    <Input Event="CapPitchDown" Name="UI_Event_PitchDown" Tooltip="UI_Event_PitchDown_Tooltip" Keys="w" Type="ToggleButton" GroupID="1" Order="10500"/>
    <Input Event="CapRoll" Name="UI_Event_Roll" Tooltip="UI_Event_Roll_Tooltip" SecKeys="joystick1axis2" Type="AxisX" GroupID="1" Order="10600"/>
    <Input Event="CapRollLeft" Name="UI_Event_RollLeft" Tooltip="UI_Event_RollLeft_Tooltip" Keys="q" Type="ToggleButton" GroupID="1" Order="10700"/>
    <Input Event="CapRollRight" Name="UI_Event_RollRight" Tooltip="UI_Event_RollRight_Tooltip" Keys="e" Type="ToggleButton" GroupID="1" Order="10800"/>
    <Input Event="CapStrafeX" Name="UI_Event_StrafeX" Tooltip="UI_Event_StrafeX_Tooltip" SecKeys="joystick0axis0" Type="AxisX" GroupID="1" Order="10900"/>
    <Input Event="CapStrafeLeft" Name="UI_Event_StrafeLeft" Tooltip="UI_Event_StrafeLeft_Tooltip" Keys="leftctrl + a" Type="ToggleButton" GroupID="1" Order="11000"/>
    <Input Event="CapStrafeRight" Name="UI_Event_StrafeRight" Tooltip="UI_Event_StrafeRight_Tooltip" Keys="leftctrl + d" Type="ToggleButton" GroupID="1" Order="11100"/>
    <Input Event="CapStrafeY" Name="UI_Event_StrafeY" Tooltip="UI_Event_StrafeY_Tooltip" SecKeys="joystick0axis2" Type="AxisY" GroupID="1" Order="11200"/>
    <Input Event="CapStrafeUp" Name="UI_Event_StrafeUp" Tooltip="UI_Event_StrafeUp_Tooltip" Keys="r" Type="ToggleButton" GroupID="1" Order="11300"/>
    <Input Event="CapStrafeDown" Name="UI_Event_StrafeDown" Tooltip="UI_Event_StrafeDown_Tooltip" Keys="f" Type="ToggleButton" GroupID="1" Order="11400"/>
    <Input Event="CapStrafeZ" Name="UI_Event_StrafeZ" Tooltip="UI_Event_StrafeZ_Tooltip" SecKeys="joystick0axis1" Type="AxisY" GroupID="1" Order="11500"/>
    <Input Event="CapForward" Name="UI_Event_Forward" Tooltip="UI_Event_Forward_Tooltip" Keys="leftctrl + w" Type="ToggleButton" GroupID="1" Order="11600"/>
    <Input Event="CapBackward" Name="UI_Event_Backward" Tooltip="UI_Event_Backward_Tooltip" Keys="leftctrl + s" Type="ToggleButton" GroupID="1" Order="11700"/>
    <Input Event="CapshipAutoTurn" Name="UI_Event_CapshipAutoTurn" Tooltip="UI_Event_CapshipAutoTurn_Tooltip" Keys="space" Type="ToggleButton" GroupID="1" Order="11800"/>
    <Input Event="CapshipTurn" Name="UI_Event_CapshipTurn" Tooltip="UI_Event_CapshipTurn_Tooltip" Keys="leftshift" Type="ToggleButton" GroupID="1" Order="11900"/>
    <Input Event="CapViewYaw" Name="UI_Event_ViewYaw" Tooltip="UI_Event_ViewYaw_Tooltip" Keys="mouseaxisx" SecKeys="joystick0arrow0" Type="AxisX" GroupID="1" Order="12000"/>
    <Input Event="CapViewPitch" Name="UI_Event_ViewPitch" Tooltip="UI_Event_ViewPitch_Tooltip" Keys="mouseaxisy" SecKeys="joystick0arrow0" Type="AxisY" GroupID="1" Order="12100"/>
    <Input Event="SetTargetSpeed" Name="UI_Event_SetTargetSpeed" Tooltip="UI_Event_SetTargetSpeed_Tooltip" Reverse="true" Type="Throttle" GroupID="2" Order="20000"/>
    <Input Event="TargetSpeed0" Name="UI_Event_TargetSpeed0" Tooltip="UI_Event_TargetSpeed0_Tooltip" Keys="leftctrl + 1" Type="ToggleButton" GroupID="2" Order="20100"/>
    <Input Event="TargetSpeed1" Name="UI_Event_TargetSpeed1" Tooltip="UI_Event_TargetSpeed1_Tooltip" Keys="leftctrl + 2" Type="ToggleButton" GroupID="2" Order="20200"/>
    <Input Event="TargetSpeed2" Name="UI_Event_TargetSpeed2" Tooltip="UI_Event_TargetSpeed2_Tooltip" Keys="leftctrl + 3" Type="ToggleButton" GroupID="2" Order="20300"/>
    <Input Event="TargetSpeed3" Name="UI_Event_TargetSpeed3" Tooltip="UI_Event_TargetSpeed3_Tooltip" Keys="leftctrl + 4" Type="ToggleButton" GroupID="2" Order="20400"/>
    <Input Event="TargetSpeed4" Name="UI_Event_TargetSpeed4" Tooltip="UI_Event_TargetSpeed4_Tooltip" Keys="leftctrl + 5" Type="ToggleButton" GroupID="2" Order="20500"/>
    <Input Event="TargetSpeed5" Name="UI_Event_TargetSpeed5" Tooltip="UI_Event_TargetSpeed5_Tooltip" Keys="leftctrl + 6" Type="ToggleButton" GroupID="2" Order="20600"/>
    <Input Event="TargetSpeed6" Name="UI_Event_TargetSpeed6" Tooltip="UI_Event_TargetSpeed6_Tooltip" Keys="leftctrl + 7" Type="ToggleButton" GroupID="2" Order="20700"/>
    <Input Event="TargetSpeed7" Name="UI_Event_TargetSpeed7" Tooltip="UI_Event_TargetSpeed7_Tooltip" Keys="leftctrl + 8" Type="ToggleButton" GroupID="2" Order="20800"/>
    <Input Event="TargetSpeed8" Name="UI_Event_TargetSpeed8" Tooltip="UI_Event_TargetSpeed8_Tooltip" Keys="leftctrl + 9" Type="ToggleButton" GroupID="2" Order="20900"/>
    <Input Event="TargetSpeed9" Name="UI_Event_TargetSpeed9" Tooltip="UI_Event_TargetSpeed9_Tooltip" Keys="leftctrl + 0" Type="ToggleButton" GroupID="2" Order="21000"/>
    <Input Event="DeltaTargetSpeed" Name="UI_Event_DeltaTargetSpeed" Tooltip="UI_Event_DeltaTargetSpeed_Tooltip" Keys="mousewheel" SecKeys="joystick0axis3" Reverse="true" Type="AxisY" GroupID="2" Order="21100"/>
    <Input Event="IncrTargetSpeed" Name="UI_Event_IncrTargetSpeed" Tooltip="UI_Event_IncrTargetSpeed_Tooltip" Keys="keypadplus" Type="ToggleButton" GroupID="2" Order="21200"/>
    <Input Event="DecrTargetSpeed" Name="UI_Event_DecrTargetSpeed" Tooltip="UI_Event_DecrTargetSpeedTooltip" Keys="keypadminus" Type="ToggleButton" GroupID="2" Order="21300"/>
    <Input Event="PrevTargetSpeed" Name="UI_Event_PrevTargetSpeed" Tooltip="UI_Event_PrevTargetSpeed_Tooltip" Keys="pagedown" Type="ToggleButton" GroupID="2" Order="21500"/>
    <Input Event="NextTargetSpeed" Name="UI_Event_NextTargetSpeed" Tooltip="UI_Event_NextTargetSpeed_Tooltip" Keys="pageup" Type="ToggleButton" GroupID="2" Order="21400"/>
    <Input Event="ReverseFlight" Name="UI_Event_ReverseFlight" Tooltip="UI_Event_ReverseFlight_Tooltip" Type="ToggleButton" GroupID="2" Order="21600"/>
    <Input Event="AutoAssist" Name="UI_Event_AutoAssist" Tooltip="UI_Event_AutoAssist_Tooltip" Keys="backslash" SecKeys="joystick0button2" Type="ToggleButton" GroupID="2" Order="21700"/>
    <Input Event="RotationAssist" Name="UI_Event_RotationAssist" Tooltip="UI_Event_RotationAssist_Tooltip" Type="ToggleButton" GroupID="2" Order="21800"/>
    <Input Event="SwitchFormation" Name="UI_Event_SwitchFormation" Tooltip="UI_Event_SwitchFormation_Tooltip" Keys="b" SecKeys="joystick0button1" Type="ToggleButton" GroupID="2" Order="21900"/>
    <Input Event="SwitchFormationFree" Name="UI_Event_SwitchFormationFree" Tooltip="UI_Event_SwitchFormationFree_Tooltip" Type="ToggleButton" GroupID="2" Order="22000"/>
    <Input Event="SwitchFormationMatchVelocity" Name="UI_Event_SwitchFormationMatchVelocity" Tooltip="UI_Event_SwitchFormationMatchVelocity_Tooltip" Type="ToggleButton" GroupID="2" Order="22100"/>
    <Input Event="SwitchFormationChaseBehind" Name="UI_Event_SwitchFormationChaseBehind" Tooltip="UI_Event_SwitchFormationChaseBehind_Tooltip" Type="ToggleButton" GroupID="2" Order="22200"/>
    <Input Event="SwitchFormationFixed" Name="UI_Event_SwitchFormationFixed" Tooltip="UI_Event_SwitchFormationFixed_Tooltip" Type="ToggleButton" GroupID="2" Order="22300"/>
    <Input Event="SwitchFormationOrbit" Name="UI_Event_SwitchFormationOrbit" Tooltip="UI_Event_SwitchFormationOrbit_Tooltip" Type="ToggleButton" GroupID="2" Order="22400"/>
    <Input Event="PrimaryFire" Name="UI_Event_PrimaryFire" Tooltip="UI_Event_PrimaryFire_Tooltip" Keys="mousebuttonleft" SecKeys="joystick1button0" Type="AnalogButton" GroupID="3" Order="30000"/>
    <Input Event="ChaffFire" Name="UI_Event_ChaffFire" Tooltip="UI_Event_ChaffFire_Tooltip" Keys="mousebuttonmiddle" SecKeys="joystick1button2" Type="ToggleButton" GroupID="3" Order="30300"/>
    <Input Event="WeaponsMenu" Name="UI_Event_Weapons_Menu" Tooltip="UI_Event_Weapons_Menu_Tooltip" Keys="mousebuttonright" Type="ToggleButton" GroupID="3" Order="30400"/>
    <Input Event="TargetCenter" Name="UI_Event_TargetCenter" Tooltip="UI_Event_TargetCenter_Tooltip" Keys="t" SecKeys="joystick1button16" Type="ToggleButton" GroupID="3" Order="30500"/>
    <Input Event="TargetPrev" Name="UI_Event_TargetPrev" Tooltip="UI_Event_TargetPrev_Tooltip" Keys="y" SecKeys="joystick1button19" Type="ToggleButton" GroupID="3" Order="30700"/>
    <Input Event="TargetNext" Name="UI_Event_TargetNext" Tooltip="UI_Event_TargetNext_Tooltip" Keys="u" SecKeys="joystick1button17" Type="ToggleButton" GroupID="3" Order="30600"/>
    <Input Event="TargetClosest" Name="UI_Event_TargetClosest" Tooltip="UI_Event_TargetClosest_Tooltip" Keys="g" SecKeys="joystick0button0 + rightctrl + joystick1button16" Type="ToggleButton" GroupID="3" Order="30800"/>
    <Input Event="TargetNone" Name="UI_Event_TargetNone" Tooltip="UI_Event_TargetNone_Tooltip" Keys="backspace" Type="ToggleButton" GroupID="3" Order="30900"/>
    <Input Event="SubTargetCenter" Name="UI_Event_SubTargetCenter" Tooltip="UI_Event_SubTargetCenter_Tooltip" Keys="leftalt + t" Type="ToggleButton" GroupID="3" Order="30550"/>
    <Input Event="SubTargetPrev" Name="UI_Event_SubTargetPrev" Tooltip="UI_Event_SubTargetPrev_Tooltip" Keys="leftalt + y" Type="ToggleButton" GroupID="3" Order="30750"/>
    <Input Event="SubTargetNext" Name="UI_Event_SubTargetNext" Tooltip="UI_Event_SubTargetNext_Tooltip" Keys="leftalt + u" Type="ToggleButton" GroupID="3" Order="30650"/>
    <Input Event="TargetClosestAlly" Name="UI_Event_TargetClosestAlly" Tooltip="UI_Event_TargetClosestAlly_Tooltip" Keys="leftalt + g" SecKeys="joystick1button18" Type="ToggleButton" GroupID="3" Order="30850"/>
    <Input Event="SafetyLock" Name="UI_Event_SafetyLock" Tooltip="UI_Event_SafetyLock_Tooltip" SecKeys="joystick0button0 + rightctrl + joystick1button0" Type="ToggleButton" GroupID="3" Order="31000"/>
    <Input Event="WeaponGroup0" Name="UI_Event_WeaponGroup0" Tooltip="UI_Event_WeaponGroup0_Tooltip" Keys="1" Type="ToggleButton" GroupID="3" Order="31100"/>
    <Input Event="WeaponGroup1" Name="UI_Event_WeaponGroup1" Tooltip="UI_Event_WeaponGroup1_Tooltip" Keys="2" Type="ToggleButton" GroupID="3" Order="31200"/>
    <Input Event="WeaponGroup2" Name="UI_Event_WeaponGroup2" Tooltip="UI_Event_WeaponGroup2_Tooltip" Keys="3" Type="ToggleButton" GroupID="3" Order="31300"/>
    <Input Event="WeaponGroup3" Name="UI_Event_WeaponGroup3" Tooltip="UI_Event_WeaponGroup3_Tooltip" Keys="4" Type="ToggleButton" GroupID="3" Order="31400"/>
    <Input Event="WeaponGroup4" Name="UI_Event_WeaponGroup4" Tooltip="UI_Event_WeaponGroup4_Tooltip" Keys="5" Type="ToggleButton" GroupID="3" Order="31500"/>
    <Input Event="WeaponGroup5" Name="UI_Event_WeaponGroup5" Tooltip="UI_Event_WeaponGroup5_Tooltip" Keys="6" Type="ToggleButton" GroupID="3" Order="31600"/>
    <Input Event="WeaponGroup6" Name="UI_Event_WeaponGroup6" Tooltip="UI_Event_WeaponGroup6_Tooltip" Keys="7" Type="ToggleButton" GroupID="3" Order="31700"/>
    <Input Event="WeaponGroup7" Name="UI_Event_WeaponGroup7" Tooltip="UI_Event_WeaponGroup7_Tooltip" Keys="8" Type="ToggleButton" GroupID="3" Order="31800"/>
    <Input Event="WeaponGroup8" Name="UI_Event_WeaponGroup8" Tooltip="UI_Event_WeaponGroup8_Tooltip" Keys="9" Type="ToggleButton" GroupID="3" Order="31900"/>
    <Input Event="WeaponGroup9" Name="UI_Event_WeaponGroup9" Tooltip="UI_Event_WeaponGroup9_Tooltip" Keys="0" Type="ToggleButton" GroupID="3" Order="32000"/>
    <Input Event="GameMenu" Name="UI_Event_Game_Menu" Tooltip="UI_Event_Game_Menu_Tooltip" Keys="tab" SecKeys="joystick0button10" Type="ToggleButton" GroupID="4" Order="40000"/>
    <Input Event="SystemsMenu" Name="UI_Event_Systems_Menu" Tooltip="UI_Event_Systems_Menu_Tooltip" Keys="v" SecKeys="joystick0button11" Type="ToggleButton" GroupID="4" Order="40100"/>
    <Input Event="CommsMenu" Name="UI_Event_Comms_Menu" Tooltip="UI_Event_Comms_Menu_Tooltip" Keys="c" SecKeys="joystick0button13" Type="ToggleButton" GroupID="4" Order="40200"/>
    <Input Event="Warp" Name="UI_Event_Warp" Tooltip="UI_Event_Warp_Tooltip" Keys="j" SecKeys="joystick0button7" Type="ToggleButton" GroupID="4" Order="40300"/>
    <Input Event="Radar" Name="UI_Event_Radar" Tooltip="UI_Event_Radar_Tooltip" Keys="quote" SecKeys="joystick0button4" Type="ToggleButton" GroupID="4" Order="40400"/>
    <Input Event="Power" Name="UI_Event_Power" Tooltip="UI_Event_Power_Tooltip" Keys="p" SecKeys="joystick0button8" Type="ToggleButton" GroupID="4" Order="40500"/>
    <Input Event="FrontLights" Name="UI_Event_FrontLights" Tooltip="UI_Event_FrontLights_Tooltip" Keys="l" SecKeys="joystick0button9" Type="ToggleButton" GroupID="4" Order="40600"/>
    <Input Event="PrevScanFreq" Name="UI_Event_PrevScanFreq" Tooltip="UI_Event_PrevScanFreq_Tooltip" Keys="leftctrl + y" SecKeys="joystick0button0 + rightctrl + joystick0button6" Type="ToggleButton" GroupID="4" Order="40800"/>
    <Input Event="NextScanFreq" Name="UI_Event_NextScanFreq" Tooltip="UI_Event_NextScanFreq_Tooltip" Keys="leftctrl + u" SecKeys="joystick0button6" Type="ToggleButton" GroupID="4" Order="40700"/>
    <Input Event="SwitchOvercharge" Name="UI_Event_SwitchOvercharge" Tooltip="UI_Event_SwitchOvercharge_Tooltip" SecKeys="joystick1button14" Type="ToggleButton" GroupID="4" Order="40900"/>
    <Input Event="SwitchOverchargeOff" Name="UI_Event_SwitchOverchargeOff" Tooltip="UI_Event_SwitchOverchargeOff_Tooltip" SecKeys="joystick1button13" Type="ToggleButton" GroupID="4" Order="41000"/>
    <Input Event="SwitchOverchargeEngine" Name="UI_Event_SwitchOverchargeEngine" Tooltip="UI_Event_SwitchOverchargeEngine_Tooltip" SecKeys="joystick1button12" Type="ToggleButton" GroupID="4" Order="41100"/>
    <Input Event="SwitchOverchargeShields" Name="UI_Event_SwitchOverchargeShields" Tooltip="UI_Event_SwitchOverchargeShields_Tooltip" SecKeys="joystick1button11" Type="ToggleButton" GroupID="4" Order="41200"/>
    <Input Event="SwitchOverchargeWeapons" Name="UI_Event_SwitchOverchargeWeapons" Tooltip="UI_Event_SwitchOverchargeWeapons_Tooltip" SecKeys="joystick1button10" Type="ToggleButton" GroupID="4" Order="41300"/>
    <Input Event="CameraCockpitMode" Name="UI_Event_CameraCockpitMode" Tooltip="UI_Event_CameraCockpitMode_Tooltip" Keys="f1" SecKeys="joystick1button4" Type="ToggleButton" GroupID="5" Order="50000"/>
    <Input Event="CameraExternalMode" Name="UI_Event_CameraExternalMode" Tooltip="UI_Event_CameraExternalMode_Tooltip" Keys="f2" SecKeys="joystick1button5" Type="ToggleButton" GroupID="5" Order="50100"/>
    <Input Event="CameraNextMode" Name="UI_Event_CameraNextMode" Tooltip="UI_Event_CameraNextMode_Tooltip" SecKeys="joystick1button6" Type="ToggleButton" GroupID="5" Order="50200"/>
    <Input Event="ViewReset" Name="UI_Event_ViewReset" Tooltip="UI_Event_ViewReset_Tooltip" Keys="leftctrl" DoubleTap="true" Type="ToggleButton" GroupID="5" Order="50300"/>
    <Input Event="ViewDist" Name="UI_Event_ViewDist" Tooltip="UI_Event_ViewDist_Tooltip" Keys="leftctrl + mousewheel" SecKeys="joystick1axis3" Type="Throttle" GroupID="5" Order="50400"/>
    <Input Event="Zoom" Name="UI_Event_Zoom" Tooltip="UI_Event_Zoom_Tooltip" Keys="z" SecKeys="joystick1button9" Type="ToggleButton" GroupID="5" Order="50500"/>
    <Input Event="CycleZoomMode" Name="UI_Event_CycleZoomMode" Tooltip="UI_Event_CycleZoomMode_Tooltip" SecKeys="rightctrl + joystick0button0 + joystick1button9" Type="ToggleButton" GroupID="5" Order="50600"/>
    <Input Event="CursorX" Name="UI_Event_CursorX" Tooltip="UI_Event_CursorX_Tooltip" Keys="mouseaxisx" Type="AxisX" GroupID="6" Order="60000"/>
    <Input Event="CursorY" Name="UI_Event_CursorY" Tooltip="UI_Event_CursorY_Tooltip" Keys="mouseaxisy" Type="AxisY" GroupID="6" Order="60100"/>
    <Input Event="Select" Name="UI_Event_Select" Tooltip="UI_Event_Select_Tooltip" Keys="space" SecKeys="joystick1button0" Type="ToggleButton" GroupID="6" Order="60200"/>
    <Input Event="Back" Name="UI_Event_Back" Tooltip="UI_Event_Back_Tooltip" Keys="escape" Type="ToggleButton" GroupID="6" Order="60300" IgnoreConflicts="MainMenu"/>
    <Input Event="Previous" Name="UI_Event_Previous" Tooltip="UI_Event_Previous_Tooltip" SecKeys="joystick1button19" Type="ToggleButton" GroupID="6" Order="60500"/>
    <Input Event="Next" Name="UI_Event_Next" Tooltip="UI_Event_Next_Tooltip" SecKeys="joystick1button17" Type="ToggleButton" GroupID="6" Order="60400"/>
    <Input Event="MainMenu" Name="UI_Event_Main_Menu" Tooltip="UI_Event_Main_Menu_Tooltip" Keys="escape" Type="ToggleButton" GroupID="6" Order="60600"/>
    <Input Event="Exit" Name="UI_Event_Exit" Tooltip="UI_Event_Exit_Tooltip" Keys="leftalt + f4" Type="ToggleButton" GroupID="6" Order="60700"/>
    <Input Event="KeyboardMap" Name="UI_Event_KeyboardMap" Tooltip="UI_Event_KeyboardMap_Tooltip" Keys="f9" SecKeys="joystick1button8" Type="ToggleButton" GroupID="6" Order="60800"/>
    <Input Event="Screenshot" Name="UI_Event_Screenshot" Tooltip="UI_Event_Screenshot_Tooltip" Keys="f11" SecKeys="joystick0button15" Type="ToggleButton" GroupID="6" Order="60900"/>
    <Input Event="Debug" Name="UI_Event_Debug" Tooltip="UI_Event_Debug_Tooltip" Keys="f10" Type="ToggleButton" GroupID="6" Order="61000"/>
    <Input Event="HUDMode" Name="UI_Event_HUDMode" Tooltip="UI_Event_HUDMode_Tooltip" Keys="f3" SecKeys="joystick1button7" Type="ToggleButton" GroupID="6" Order="61100"/>
    <Input Event="MFD" Name="UI_Event_MFD" Tooltip="UI_Event_MFD_Tooltip" Keys="f4" Type="ToggleButton" GroupID="6" Order="61150"/>
    <Input Event="Music" Name="UI_Event_Music" Tooltip="UI_Event_Music_Tooltip" Type="ToggleButton" GroupID="6" Order="61200"/>
    <Input Event="MineFire" Name="UI_Event_MineFire" Tooltip="UI_Event_MineFire_Tooltip" Keys="m" SecKeys="joystick1button3" Type="ToggleButton" GroupID="3" Order="30350"/>
    <Input Event="ScanMode" Name="UI_Event_ScanMode" Tooltip="UI_Event_ScanMode_Tooltip" SecKeys="joystick0button5" Type="ToggleButton" GroupID="4" Order="40650"/>
    <Input Event="CycleWeapons" Name="UI_Event_CycleWeapons" Tooltip="UI_Event_CycleWeapons_Tooltip" SecKeys="joystick1button1" Type="ToggleButton" GroupID="3" Order="30100"/>
    <Input Event="FlightMenu" Name="UI_Event_Flight_Menu" Tooltip="UI_Event_Flight_Menu_Tooltip" Keys="x" SecKeys="joystick0button12" Type="ToggleButton" GroupID="4" Order="40150"/>
    <Input Event="ViewLeft" Name="UI_Event_ViewLeft" Tooltip="UI_Event_ViewLeft_Tooltip" Keys="keypad4" Type="ToggleButton" GroupID="5" Order="50450"/>
    <Input Event="ViewRight" Name="UI_Event_ViewRight" Tooltip="UI_Event_ViewRight_Tooltip" Keys="keypad6" Type="ToggleButton" GroupID="5" Order="50455"/>
    <Input Event="ViewCenter" Name="UI_Event_ViewCenter" Tooltip="UI_Event_ViewCenter_Tooltip" Keys="keypad5" Type="ToggleButton" GroupID="5" Order="50460"/>
    <Input Event="ViewDown" Name="UI_Event_ViewDown" Tooltip="UI_Event_ViewDown_Tooltip" Keys="keypad2" Type="ToggleButton" GroupID="5" Order="50465"/>
    <Input Event="ViewUp" Name="UI_Event_ViewUp" Tooltip="UI_Event_ViewUp_Tooltip" Keys="keypad8" Type="ToggleButton" GroupID="5" Order="50470"/>
</InputMapper>
